e_peen/__init__.py
e_peen/app.py
E_Peen-1.2.0.dist-info/METADATA
E_Peen-1.2.0.dist-info/WHEEL
E_Peen-1.2.0.dist-info/entry_points.txt
E_Peen-1.2.0.dist-info/top_level.txt
E_Peen-1.2.0.dist-info/RECORD
