Metadata-Version: 2.1
Name: E-Peen
Version: 1.2.0
Summary: A benchmarking tool (CPU, GPU, RAM, Storage) to measure your e-peen.
Home-page: https://github.com/crosschainer/e-peen
Author: crosschainer
Author-email: cross@xian.org
Classifier: Programming Language :: Python :: 3
Classifier: License :: OSI Approved :: MIT License
Classifier: Operating System :: OS Independent
Requires-Python: >=3.11
Requires-Dist: pyopencl
Requires-Dist: numpy
Requires-Dist: rich
